django_public_admin/__init__.py
django_public_admin/admin.py
django_public_admin/apps.py
django_public_admin/templates/admin/base_site.html
django_public_admin/templates/public_admin/index.html
django_public_admin_mixins-0.0.1.dist-info/METADATA
django_public_admin_mixins-0.0.1.dist-info/WHEEL
django_public_admin_mixins-0.0.1.dist-info/licenses/LICENSE.txt
django_public_admin_mixins-0.0.1.dist-info/RECORD
